loadbearing_wall/__init__.py
loadbearing_wall/geom_ops.py
loadbearing_wall/linear_reactions.py
loadbearing_wall/point_reactions.py
loadbearing_wall/wall_model.py
loadbearing_wall-0.5.0.dist-info/WHEEL
loadbearing_wall-0.5.0.dist-info/METADATA
loadbearing_wall-0.5.0.dist-info/RECORD
