Metadata-Version: 2.4
Name: loadbearing-wall
Version: 0.5.0
Summary: A package that models a generic load-bearing wall for the purpose of determining
Author-email: Connor Ferster <connor@structuralpython.com>
Requires-Python: >=3.11
Requires-Dist: load-distribution>=0.1.7
Requires-Dist: pydantic>=2.0.0
Requires-Dist: safer>=5.1.0
